fcbf/__init__.py
fcbf/data/__init__.py
fcbf/data/datasets.py
fcbf/data/lung-cancer.data
fcbf/fcbf.py
fcbf-0.1.2.dist-info/LICENSE
fcbf-0.1.2.dist-info/METADATA
fcbf-0.1.2.dist-info/WHEEL
fcbf-0.1.2.dist-info/RECORD
