Metadata-Version: 2.1
Name: fcbf
Version: 0.1.2
Summary: Categorical feature selection based on information theoretical considerations
Home-page: https://github.com/m-martin-j/fcbf
License: MIT
Author: Martin Trat
Author-email: martin.trat@gmail.com
Requires-Python: >=3.9,<4.0
Classifier: Development Status :: 2 - Pre-Alpha
Classifier: License :: OSI Approved :: MIT License
Classifier: Programming Language :: Python :: 3
Classifier: Programming Language :: Python :: 3.9
Classifier: Programming Language :: Python :: 3.10
Classifier: Programming Language :: Python :: 3.11
Classifier: Programming Language :: Python :: 3.12
Classifier: Topic :: Scientific/Engineering :: Artificial Intelligence
Requires-Dist: numpy (>=1.26.4,<2.0.0)
Requires-Dist: pandas (>=2.2.2,<3.0.0)
Requires-Dist: scipy (>=1.13.0,<2.0.0)
Project-URL: Repository, https://github.com/m-martin-j/fcbf
